truce
