Metadata-Version: 1.1
Name: truce
Version: 0.2.1
Summary: An experimental text editor and/or shell
Home-page: https://github.com/jangler/truce-py
Author: Brandon Mulcahy
Author-email: brandon@jangler.info
License: MIT
Keywords: truce,text,editor,shell,tkinter
Platform: UNKNOWN
Classifier: Development Status :: 3 - Alpha
Classifier: Intended Audience :: Developers
Classifier: Intended Audience :: End Users/Desktop
Classifier: Topic :: System :: Shells
Classifier: Topic :: Text Editors
Classifier: License :: OSI Approved :: MIT License
Classifier: Programming Language :: Python
Classifier: Programming Language :: Python :: 3
Classifier: Programming Language :: Python :: 3 :: Only
Classifier: Operating System :: OS Independent
